openplxbundles/DriveTrain/Actuator.openplx
openplxbundles/DriveTrain/AutomaticBrake.openplx
openplxbundles/DriveTrain/AutomaticClutch.openplx
openplxbundles/DriveTrain/Differential.openplx
openplxbundles/DriveTrain/EmpiricalEngine.openplx
openplxbundles/DriveTrain/EmpiricalTorqueConverter.openplx
openplxbundles/DriveTrain/Engines/Cat-C17520.openplx
openplxbundles/DriveTrain/Engines/Cat-C27.openplx
openplxbundles/DriveTrain/Engines/Cat-C32ACERT.openplx
openplxbundles/DriveTrain/Engines/Doosan-DE08TIS.openplx
openplxbundles/DriveTrain/Engines/GMTruck.openplx
openplxbundles/DriveTrain/Engines/JohnDeere-6068HF485.openplx
openplxbundles/DriveTrain/Engines/Komatsu-WA475-10.openplx
openplxbundles/DriveTrain/Engines/Saab-B234i.openplx
openplxbundles/DriveTrain/Engines/Scania-K310UB4X2Euro5.openplx
openplxbundles/DriveTrain/Engines/Volvo-BMTD45B.openplx
openplxbundles/DriveTrain/Engines/Volvo-D16E540.openplx
openplxbundles/DriveTrain/Engines/Volvo-T5.openplx
openplxbundles/DriveTrain/Engines/Volvo-TD73KD.openplx
openplxbundles/DriveTrain/FlexibleGear.openplx
openplxbundles/DriveTrain/Gear.openplx
openplxbundles/DriveTrain/GearBox.openplx
openplxbundles/DriveTrain/HingeActuator.openplx
openplxbundles/DriveTrain/InfinitePowerSource.openplx
openplxbundles/DriveTrain/ManualBrake.openplx
openplxbundles/DriveTrain/ManualClutch.openplx
openplxbundles/DriveTrain/MeanValueEngine.openplx
openplxbundles/DriveTrain/MechanicalDriveTrains/TwoWheelTemplate.openplx
openplxbundles/DriveTrain/PowerSource.openplx
openplxbundles/DriveTrain/PrismaticActuator.openplx
openplxbundles/DriveTrain/Shaft.openplx
openplxbundles/DriveTrain/Signals/AutomaticClutchDisengagementDurationInput.openplx
openplxbundles/DriveTrain/Signals/AutomaticClutchDisengagementDurationOutput.openplx
openplxbundles/DriveTrain/Signals/AutomaticClutchEngagementDurationInput.openplx
openplxbundles/DriveTrain/Signals/AutomaticClutchEngagementDurationOutput.openplx
openplx_bundles-0.18.8.dist-info/LICENSE
openplx_bundles-0.18.8.dist-info/METADATA
openplx_bundles-0.18.8.dist-info/WHEEL
openplx_bundles-0.18.8.dist-info/RECORD
