Metadata-Version: 2.1
Name: openplx-bundles
Version: 0.18.8
Summary: OpenPlx Bundles package, i.e. all OpenPLX sourcefiles and convenience access method in a package
License: Apache 2.0
Author: Algoryx
Author-email: algoryx@algoryx.com
Requires-Python: >=3.8
Classifier: License :: Other/Proprietary License
Classifier: Programming Language :: Python :: 3
Classifier: Programming Language :: Python :: 3.8
Classifier: Programming Language :: Python :: 3.9
Classifier: Programming Language :: Python :: 3.10
Classifier: Programming Language :: Python :: 3.11
Classifier: Programming Language :: Python :: 3.12
Classifier: Programming Language :: Python :: 3.13
